LICENSE
README.md
setup.py
holepunch/__init__.py
holepunch/version.py
holepunch.egg-info/PKG-INFO
holepunch.egg-info/SOURCES.txt
holepunch.egg-info/dependency_links.txt
holepunch.egg-info/entry_points.txt
holepunch.egg-info/requires.txt
holepunch.egg-info/top_level.txt