Metadata-Version: 2.1
Name: holepunch
Version: 0.9.0
Summary: Punch holes in your AWS account security
Home-page: https://github.com/erik/holepunch
Author: Erik Price
License: MIT
Platform: UNKNOWN
License-File: LICENSE
